odoo10_addon_product_replenishment_cost-10.0.1.0.0.99.dev4-py3.8-nspkg.pth
odoo/addons/product_replenishment_cost/README.rst
odoo/addons/product_replenishment_cost/__init__.py
odoo/addons/product_replenishment_cost/__manifest__.py
odoo/addons/product_replenishment_cost/demo/res_groups.xml
odoo/addons/product_replenishment_cost/i18n/es.po
odoo/addons/product_replenishment_cost/i18n/fr.po
odoo/addons/product_replenishment_cost/i18n/nl.po
odoo/addons/product_replenishment_cost/i18n/product_replenishment_cost.pot
odoo/addons/product_replenishment_cost/models/__init__.py
odoo/addons/product_replenishment_cost/models/product_product.py
odoo/addons/product_replenishment_cost/readme/CONTRIBUTORS.rst
odoo/addons/product_replenishment_cost/readme/DESCRIPTION.rst
odoo/addons/product_replenishment_cost/static/description/icon.png
odoo/addons/product_replenishment_cost/static/description/index.html
odoo/addons/product_replenishment_cost/test/cost_price_update.yml
odoo/addons/product_replenishment_cost/views/product_view.xml
odoo10_addon_product_replenishment_cost-10.0.1.0.0.99.dev4.dist-info/METADATA
odoo10_addon_product_replenishment_cost-10.0.1.0.0.99.dev4.dist-info/WHEEL
odoo10_addon_product_replenishment_cost-10.0.1.0.0.99.dev4.dist-info/namespace_packages.txt
odoo10_addon_product_replenishment_cost-10.0.1.0.0.99.dev4.dist-info/top_level.txt
odoo10_addon_product_replenishment_cost-10.0.1.0.0.99.dev4.dist-info/RECORD
